verarandom/__init__.py
verarandom/_build_utils.py
verarandom/_random_generator.py
verarandom/_utils.py
verarandom/errors.py
verarandom/random_org_v1.py
verarandom-2.0.1.dist-info/METADATA
verarandom-2.0.1.dist-info/RECORD
verarandom-2.0.1.dist-info/WHEEL
verarandom-2.0.1.dist-info/top_level.txt
