Metadata-Version: 2.1
Name: verarandom
Version: 2.0.1
Summary: True random numbers in Python
Home-page: https://github.com/AliGhahraei/verarandom
Author: Ali Ghahraei Figueroa
Author-email: aligf94@gmail.com
License: MIT
Platform: UNKNOWN
Classifier: Programming Language :: Python :: 3
Classifier: License :: OSI Approved :: MIT License
Classifier: Operating System :: OS Independent
Classifier: Topic :: Scientific/Engineering :: Mathematics
Requires-Dist: requests
